mail_control/__init__.py
mail_control-0.2.0.dist-info/DESCRIPTION.rst
mail_control-0.2.0.dist-info/METADATA
mail_control-0.2.0.dist-info/RECORD
mail_control-0.2.0.dist-info/WHEEL
mail_control-0.2.0.dist-info/metadata.json
mail_control-0.2.0.dist-info/top_level.txt
