Metadata-Version: 2.0
Name: mail-control
Version: 0.2.0
Summary: Mail Control, Easy to use python, Easy to send mail
Home-page: https://windard.com
Author: Windard Yang
Author-email: windard@qq.com
License: MIT
Keywords: Mail Control To Send Mail
Platform: UNKNOWN
Requires-Python: >=2.6
